var data={"type":"Feature","id":99,"geometry":{"type":"Point","coordinates":[-8.7384152526145904,41.796261587628265]},"properties":{"FID":99,"ID":"160902","Nome":"Poço Negro - Montaria","Y":41.796300000000002,"X":-8.7383699999999997,"Distrito":"Viana do Castelo","Concelho":"Viana do Castelo","Rio":"Rio Âncora","Altura_m":"10","Area_Monta":" ","Pmadia_bac":"2250","litologia":"Xistos andaluzíticos e Granito de grão grosseiro ou médio a grosseiro","Contacto":"1","Uso":" ","Fonte":"Tese Marta","Altitude_m":249.968994141,"FID_":0,"Id_1":160902,"gridcode":99,"Area":8.9258711389399998,"Precipitac":2417,"ID_Casc":"160902","FID_1":99,"ID_12":" ","Nome_1":" ","Y_1":0,"X_1":0,"Distrito_1":" ","Concelho_1":" ","Rio_1":" ","Altura_m_1":" ","Area_Mon_1":" ","Pmadia_b_1":" ","litologi_1":" ","Contacto_1":" ","Uso_1":" ","Fonte_1":" ","Altitude_1":0,"RASTERVALU":236}}